Metadata-Version: 1.1
Name: aioamqp-ext
Version: 0.1.5
Summary: UNKNOWN
Home-page: UNKNOWN
Author: Wargaming Team
Author-email: UNKNOWN
License: UNKNOWN
Platform: UNKNOWN
Classifier: Programming Language :: Python
Classifier: Programming Language :: Python :: 3.5
Classifier: Programming Language :: Python :: 3.6
